{
    "description": "",
    "tags": [],
    "size": {
        "height": 284,
        "width": 640
    },
    "objects": [
        {
            "id": 6343599,
            "classId": 8721,
            "description": "",
            "geometryType": "rectangle",
            "labelerLogin": "az@datasetninja.com",
            "createdAt": "2023-06-13T23:43:18.694Z",
            "updatedAt": "2023-06-13T23:43:18.694Z",
            "tags": [],
            "classTitle": "pickup",
            "points": {
                "exterior": [
                    [
                        106,
                        96
                    ],
                    [
                        247,
                        237
                    ]
                ],
                "interior": []
            }
        }
    ]
}