{
    "description": "",
    "tags": [],
    "size": {
        "height": 360,
        "width": 640
    },
    "objects": [
        {
            "id": 6334309,
            "classId": 8720,
            "description": "",
            "geometryType": "rectangle",
            "labelerLogin": "az@datasetninja.com",
            "createdAt": "2023-06-13T23:40:30.615Z",
            "updatedAt": "2023-06-13T23:40:30.615Z",
            "tags": [],
            "classTitle": "motorbike",
            "points": {
                "exterior": [
                    [
                        195,
                        208
                    ],
                    [
                        639,
                        357
                    ]
                ],
                "interior": []
            }
        },
        {
            "id": 6334308,
            "classId": 8721,
            "description": "",
            "geometryType": "rectangle",
            "labelerLogin": "az@datasetninja.com",
            "createdAt": "2023-06-13T23:40:30.615Z",
            "updatedAt": "2023-06-13T23:40:30.615Z",
            "tags": [],
            "classTitle": "pickup",
            "points": {
                "exterior": [
                    [
                        72,
                        4
                    ],
                    [
                        291,
                        205
                    ]
                ],
                "interior": []
            }
        },
        {
            "id": 6334307,
            "classId": 8715,
            "description": "",
            "geometryType": "rectangle",
            "labelerLogin": "az@datasetninja.com",
            "createdAt": "2023-06-13T23:40:30.615Z",
            "updatedAt": "2023-06-13T23:40:30.615Z",
            "tags": [],
            "classTitle": "car",
            "points": {
                "exterior": [
                    [
                        333,
                        114
                    ],
                    [
                        357,
                        135
                    ]
                ],
                "interior": []
            }
        },
        {
            "id": 6334306,
            "classId": 8728,
            "description": "",
            "geometryType": "rectangle",
            "labelerLogin": "az@datasetninja.com",
            "createdAt": "2023-06-13T23:40:30.615Z",
            "updatedAt": "2023-06-13T23:40:30.615Z",
            "tags": [],
            "classTitle": "truck",
            "points": {
                "exterior": [
                    [
                        354,
                        103
                    ],
                    [
                        369,
                        122
                    ]
                ],
                "interior": []
            }
        },
        {
            "id": 6334305,
            "classId": 8715,
            "description": "",
            "geometryType": "rectangle",
            "labelerLogin": "az@datasetninja.com",
            "createdAt": "2023-06-13T23:40:30.615Z",
            "updatedAt": "2023-06-13T23:40:30.615Z",
            "tags": [],
            "classTitle": "car",
            "points": {
                "exterior": [
                    [
                        400,
                        112
                    ],
                    [
                        405,
                        115
                    ]
                ],
                "interior": []
            }
        }
    ]
}