{
    "description": "",
    "tags": [],
    "size": {
        "height": 360,
        "width": 640
    },
    "objects": [
        {
            "id": 6333173,
            "classId": 8730,
            "description": "",
            "geometryType": "rectangle",
            "labelerLogin": "az@datasetninja.com",
            "createdAt": "2023-06-13T23:40:09.396Z",
            "updatedAt": "2023-06-13T23:40:09.396Z",
            "tags": [],
            "classTitle": "wheelbarrow",
            "points": {
                "exterior": [
                    [
                        87,
                        192
                    ],
                    [
                        274,
                        261
                    ]
                ],
                "interior": []
            }
        },
        {
            "id": 6333172,
            "classId": 8720,
            "description": "",
            "geometryType": "rectangle",
            "labelerLogin": "az@datasetninja.com",
            "createdAt": "2023-06-13T23:40:09.395Z",
            "updatedAt": "2023-06-13T23:40:09.395Z",
            "tags": [],
            "classTitle": "motorbike",
            "points": {
                "exterior": [
                    [
                        471,
                        183
                    ],
                    [
                        569,
                        284
                    ]
                ],
                "interior": []
            }
        },
        {
            "id": 6333171,
            "classId": 8720,
            "description": "",
            "geometryType": "rectangle",
            "labelerLogin": "az@datasetninja.com",
            "createdAt": "2023-06-13T23:40:09.395Z",
            "updatedAt": "2023-06-13T23:40:09.395Z",
            "tags": [],
            "classTitle": "motorbike",
            "points": {
                "exterior": [
                    [
                        394,
                        153
                    ],
                    [
                        419,
                        192
                    ]
                ],
                "interior": []
            }
        },
        {
            "id": 6333170,
            "classId": 8720,
            "description": "",
            "geometryType": "rectangle",
            "labelerLogin": "az@datasetninja.com",
            "createdAt": "2023-06-13T23:40:09.393Z",
            "updatedAt": "2023-06-13T23:40:09.393Z",
            "tags": [],
            "classTitle": "motorbike",
            "points": {
                "exterior": [
                    [
                        300,
                        172
                    ],
                    [
                        349,
                        208
                    ]
                ],
                "interior": []
            }
        },
        {
            "id": 6333169,
            "classId": 8720,
            "description": "",
            "geometryType": "rectangle",
            "labelerLogin": "az@datasetninja.com",
            "createdAt": "2023-06-13T23:40:09.392Z",
            "updatedAt": "2023-06-13T23:40:09.392Z",
            "tags": [],
            "classTitle": "motorbike",
            "points": {
                "exterior": [
                    [
                        423,
                        154
                    ],
                    [
                        448,
                        167
                    ]
                ],
                "interior": []
            }
        },
        {
            "id": 6333168,
            "classId": 8727,
            "description": "",
            "geometryType": "rectangle",
            "labelerLogin": "az@datasetninja.com",
            "createdAt": "2023-06-13T23:40:09.392Z",
            "updatedAt": "2023-06-13T23:40:09.392Z",
            "tags": [],
            "classTitle": "three wheelers -CNG-",
            "points": {
                "exterior": [
                    [
                        360,
                        148
                    ],
                    [
                        382,
                        161
                    ]
                ],
                "interior": []
            }
        },
        {
            "id": 6333167,
            "classId": 8723,
            "description": "",
            "geometryType": "rectangle",
            "labelerLogin": "az@datasetninja.com",
            "createdAt": "2023-06-13T23:40:09.391Z",
            "updatedAt": "2023-06-13T23:40:09.391Z",
            "tags": [],
            "classTitle": "rickshaw",
            "points": {
                "exterior": [
                    [
                        539,
                        142
                    ],
                    [
                        564,
                        168
                    ]
                ],
                "interior": []
            }
        },
        {
            "id": 6333166,
            "classId": 8727,
            "description": "",
            "geometryType": "rectangle",
            "labelerLogin": "az@datasetninja.com",
            "createdAt": "2023-06-13T23:40:09.391Z",
            "updatedAt": "2023-06-13T23:40:09.391Z",
            "tags": [],
            "classTitle": "three wheelers -CNG-",
            "points": {
                "exterior": [
                    [
                        389,
                        147
                    ],
                    [
                        410,
                        162
                    ]
                ],
                "interior": []
            }
        },
        {
            "id": 6333165,
            "classId": 8725,
            "description": "",
            "geometryType": "rectangle",
            "labelerLogin": "az@datasetninja.com",
            "createdAt": "2023-06-13T23:40:09.388Z",
            "updatedAt": "2023-06-13T23:40:09.388Z",
            "tags": [],
            "classTitle": "suv",
            "points": {
                "exterior": [
                    [
                        301,
                        151
                    ],
                    [
                        350,
                        166
                    ]
                ],
                "interior": []
            }
        },
        {
            "id": 6333164,
            "classId": 8723,
            "description": "",
            "geometryType": "rectangle",
            "labelerLogin": "az@datasetninja.com",
            "createdAt": "2023-06-13T23:40:09.387Z",
            "updatedAt": "2023-06-13T23:40:09.387Z",
            "tags": [],
            "classTitle": "rickshaw",
            "points": {
                "exterior": [
                    [
                        617,
                        140
                    ],
                    [
                        639,
                        177
                    ]
                ],
                "interior": []
            }
        },
        {
            "id": 6333163,
            "classId": 8727,
            "description": "",
            "geometryType": "rectangle",
            "labelerLogin": "az@datasetninja.com",
            "createdAt": "2023-06-13T23:40:09.386Z",
            "updatedAt": "2023-06-13T23:40:09.386Z",
            "tags": [],
            "classTitle": "three wheelers -CNG-",
            "points": {
                "exterior": [
                    [
                        593,
                        140
                    ],
                    [
                        617,
                        161
                    ]
                ],
                "interior": []
            }
        }
    ]
}