{
    "description": "",
    "tags": [],
    "size": {
        "height": 362,
        "width": 640
    },
    "objects": [
        {
            "id": 6332548,
            "classId": 8728,
            "description": "",
            "geometryType": "rectangle",
            "labelerLogin": "az@datasetninja.com",
            "createdAt": "2023-06-13T23:39:55.337Z",
            "updatedAt": "2023-06-13T23:39:55.337Z",
            "tags": [],
            "classTitle": "truck",
            "points": {
                "exterior": [
                    [
                        369,
                        3
                    ],
                    [
                        638,
                        358
                    ]
                ],
                "interior": []
            }
        },
        {
            "id": 6332547,
            "classId": 8728,
            "description": "",
            "geometryType": "rectangle",
            "labelerLogin": "az@datasetninja.com",
            "createdAt": "2023-06-13T23:39:55.337Z",
            "updatedAt": "2023-06-13T23:39:55.337Z",
            "tags": [],
            "classTitle": "truck",
            "points": {
                "exterior": [
                    [
                        55,
                        20
                    ],
                    [
                        101,
                        76
                    ]
                ],
                "interior": []
            }
        },
        {
            "id": 6332546,
            "classId": 8714,
            "description": "",
            "geometryType": "rectangle",
            "labelerLogin": "az@datasetninja.com",
            "createdAt": "2023-06-13T23:39:55.336Z",
            "updatedAt": "2023-06-13T23:39:55.336Z",
            "tags": [],
            "classTitle": "bus",
            "points": {
                "exterior": [
                    [
                        0,
                        0
                    ],
                    [
                        29,
                        309
                    ]
                ],
                "interior": []
            }
        },
        {
            "id": 6332545,
            "classId": 8714,
            "description": "",
            "geometryType": "rectangle",
            "labelerLogin": "az@datasetninja.com",
            "createdAt": "2023-06-13T23:39:55.336Z",
            "updatedAt": "2023-06-13T23:39:55.336Z",
            "tags": [],
            "classTitle": "bus",
            "points": {
                "exterior": [
                    [
                        41,
                        22
                    ],
                    [
                        62,
                        56
                    ]
                ],
                "interior": []
            }
        },
        {
            "id": 6332544,
            "classId": 8714,
            "description": "",
            "geometryType": "rectangle",
            "labelerLogin": "az@datasetninja.com",
            "createdAt": "2023-06-13T23:39:55.336Z",
            "updatedAt": "2023-06-13T23:39:55.336Z",
            "tags": [],
            "classTitle": "bus",
            "points": {
                "exterior": [
                    [
                        28,
                        10
                    ],
                    [
                        40,
                        68
                    ]
                ],
                "interior": []
            }
        }
    ]
}